{"provides":{"HTTP::Config":{"version":"6.33","file":"lib/HTTP/Config.pm"},"HTTP::Headers::ETag":{"version":"6.33","file":"lib/HTTP/Headers/ETag.pm"},"HTTP::Status":{"version":"6.33","file":"lib/HTTP/Status.pm"},"HTTP::Request::Common":{"file":"lib/HTTP/Request/Common.pm","version":"6.33"},"HTTP::Response":{"file":"lib/HTTP/Response.pm","version":"6.33"},"HTTP::Request":{"file":"lib/HTTP/Request.pm","version":"6.33"},"HTTP::Headers::Auth":{"version":"6.33","file":"lib/HTTP/Headers/Auth.pm"},"HTTP::Message":{"file":"lib/HTTP/Message.pm","version":"6.33"},"HTTP::Headers":{"file":"lib/HTTP/Headers.pm","version":"6.33"},"HTTP::Headers::Util":{"version":"6.33","file":"lib/HTTP/Headers/Util.pm"}},"name":"HTTP::Message","version":"6.33","pathname":"O/OA/OALDERS/HTTP-Message-6.33.tar.gz","dist":"HTTP-Message-6.33","target":"HTTP::Message"}