{"provides":{"HTTP::Entity::Parser::MultiPart":{"file":"lib/HTTP/Entity/Parser/MultiPart.pm"},"HTTP::Entity::Parser::OctetStream":{"file":"lib/HTTP/Entity/Parser/OctetStream.pm"},"HTTP::Entity::Parser::UrlEncoded":{"file":"lib/HTTP/Entity/Parser/UrlEncoded.pm"},"HTTP::Entity::Parser":{"file":"lib/HTTP/Entity/Parser.pm","version":"0.25"},"HTTP::Entity::Parser::JSON":{"file":"lib/HTTP/Entity/Parser/JSON.pm"}},"name":"HTTP::Entity::Parser","version":"0.25","target":"HTTP::Entity::Parser","pathname":"K/KA/KAZEBURO/HTTP-Entity-Parser-0.25.tar.gz","dist":"HTTP-Entity-Parser-0.25"}